Metadata-Version: 1.0
Name: satori-fuse
Version: 0.1.0
Summary: The System Image Mount Tool of the Satori-Suite
Home-page: https://github.com/satori-ng/
Author: Satori-NG org
Author-email: satori_ng@email.com
License: UNKNOWN
Platform: UNKNOWN
